xmlAnomalyDetection/__init__.py
xmlAnomalyDetection/app.py
xmlAnomalyDetection/cli.py
xmlAnomalyDetection/prompts.yaml
xmlAnomalyDetection/dataset/Expense Report CPS Data.xlsx
xmlAnomalyDetection/dataset/sample.xml
xmlAnomalyDetection/parsers/__init__.py
xmlAnomalyDetection/parsers/all_parsers.py
xmlAnomalyDetection/parsers/parsers_updated.py
xmlAnomalyDetection/parsers/__pycache__/__init__.cpython-311.pyc
xmlAnomalyDetection/parsers/__pycache__/all_parsers.cpython-311.pyc
xmlAnomalyDetection-8.0.dist-info/METADATA
xmlAnomalyDetection-8.0.dist-info/WHEEL
xmlAnomalyDetection-8.0.dist-info/entry_points.txt
xmlAnomalyDetection-8.0.dist-info/top_level.txt
xmlAnomalyDetection-8.0.dist-info/RECORD
