Metadata-Version: 2.1
Name: xmlAnomalyDetection
Version: 8.0
Summary: A tool for detecting anomalies in XML data
Author: Talha Yousuf
Author-email: th05691@gmail.com
Requires-Dist: groq (==0.8.0)
Requires-Dist: langchain-groq (==0.1.4)
Requires-Dist: langchain (==0.2.1)
Requires-Dist: langchain-anthropic (==0.1.17)
Requires-Dist: langchain-astradb (==0.3.3)
Requires-Dist: langchain-aws (==0.1.9)
Requires-Dist: langchain-chroma (==0.1.2)
Requires-Dist: langchain-cohere (==0.1.8)
Requires-Dist: langchain-community (==0.2.1)
Requires-Dist: langchain-core (==0.2.28)
Requires-Dist: langchain-experimental (==0.0.59)
Requires-Dist: langchain-google-genai (==1.0.7)
Requires-Dist: langchain-google-vertexai (==1.0.6)
Requires-Dist: langchain-huggingface (==0.0.3)
Requires-Dist: langchain-mistralai (==0.1.12)
Requires-Dist: langchain-mongodb (==0.1.6)
Requires-Dist: langchain-openai (==0.1.8)
Requires-Dist: langchain-pinecone (==0.1.1)
Requires-Dist: langchain-text-splitters (==0.2.0)
Requires-Dist: langchainhub (==0.1.17)
Requires-Dist: python-dotenv (==1.0.1)
Requires-Dist: fastapi (==0.111.0)
Requires-Dist: fastapi-cli (==0.0.4)
Requires-Dist: starlette (==0.37.2)
Requires-Dist: uvicorn (==0.30.1)
Requires-Dist: pydantic (==2.8.2)
Requires-Dist: pydantic-settings (==2.3.4)
Requires-Dist: pydantic-core (==2.20.1)
Requires-Dist: loguru (==0.7.2)
